{"info":{"cache":{"id":"ucfv0j01zhkubt","f_date":"2023012700_0p50"},"local_date":"2023-01-27T14:14:20+03:00","lat":"55.7504461","lon":"37.6174943","dist":1,"elevation":156,"names":{"name":{"ru":"Москва","en":"Moscow"}},"country":"Россия"},"fact":{"obs_time":"2023-01-27T12:00:00+03:00","dist":9,"condition":"cloudy","condition_s":"облачно","temp":-3,"feels_like":-6,"comf_idx":7,"humidity":82,"pressure":751,"wind_speed_avg":2,"wind_dir":"w","light":"light","uvi":0},"forecast_24":{"0":{"sunrise":"2023-01-27T08:32:27+03:00","sunset":"2023-01-27T16:51:55+03:00","moonrise":"2023-01-27T10:49:14+03:00","moon_phase":11,"start_date":"2023-01-27T00:00:00+03:00","day":{"light":"light","condition":"cloudy_snow_0","condition_s":"облачно, небольшой снег","temp_min":-4,"temp_max":-2,"temp":-2,"humidity":92,"prec_prob":95,"wind_gust":8,"wind_speed":4,"wind_dir":"sw","pressure":752,"uvi":1,"feels_like":-6,"comf_idx":6}},"1":{"sunrise":"2023-01-28T08:30:45+03:00","sunset":"2023-01-28T16:54:00+03:00","moonrise":"2023-01-28T10:58:19+03:00","moonset":"2023-01-28T00:40:44+03:00","moon_phase":12,"start_date":"2023-01-28T00:00:00+03:00","night":{"light":"dark","condition":"partly-cloudy_snow_0","condition_s":"переменная облачность, небольшой снег","temp_min":-8,"temp_max":-3,"temp":-6,"humidity":98,"prec_prob":93,"wind_gust":5,"wind_speed":1,"wind_dir":"nw","pressure":754,"uvi":1,"feels_like":-12,"comf_idx":6},"day":{"light":"light","condition":"cloudy_snow_0","condition_s":"облачно, небольшой снег","temp_min":-7,"temp_max":-3,"temp":-3,"humidity":92,"prec_prob":93,"wind_gust":4,"wind_speed":2,"wind_dir":"se","pressure":754,"uvi":2,"feels_like":-6,"comf_idx":6}},"2":{"sunrise":"2023-01-29T08:29:00+03:00","sunset":"2023-01-29T16:56:07+03:00","moonrise":"2023-01-29T11:09:13+03:00","moonset":"2023-01-29T02:07:00+03:00","moon_phase":12,"start_date":"2023-01-29T00:00:00+03:00","night":{"light":"dark","condition":"mostly-cloudy","condition_s":"облачно с прояснениями","temp_min":-12,"temp_max":-3,"temp":-8,"humidity":96,"prec_prob":12,"wind_gust":5,"wind_speed":2,"wind_dir":"s","pressure":751,"uvi":1,"feels_like":-16,"comf_idx":6},"day":{"light":"light","condition":"mostly-cloudy","condition_s":"облачно с прояснениями","temp_min":-11,"temp_max":-4,"temp":-4,"humidity":89,"prec_prob":6,"wind_gust":8,"wind_speed":3,"wind_dir":"s","pressure":747,"uvi":2,"feels_like":-8,"comf_idx":7}},"3":{"sunrise":"2023-01-30T08:27:14+03:00","sunset":"2023-01-30T16:58:14+03:00","moonrise":"2023-01-30T11:22:48+03:00","moonset":"2023-01-30T03:33:19+03:00","moon_phase":13,"start_date":"2023-01-30T00:00:00+03:00","night":{"light":"dark","condition":"cloudy_snow_0","condition_s":"облачно, небольшой снег","temp_min":-6,"temp_max":-5,"temp":-5,"humidity":94,"prec_prob":99,"wind_gust":13,"wind_speed":5,"wind_dir":"s","pressure":742,"uvi":1,"feels_like":-12,"comf_idx":6},"day":{"light":"light","condition":"cloudy_snow_0","condition_s":"облачно, небольшой снег","temp_min":-5,"temp_max":-2,"temp":-2,"humidity":89,"prec_prob":89,"wind_gust":15,"wind_speed":7,"wind_dir":"s","pressure":737,"uvi":1,"feels_like":-8,"comf_idx":5}},"4":{"sunrise":"2023-01-31T08:25:25+03:00","sunset":"2023-01-31T17:00:22+03:00","moonrise":"2023-01-31T11:42:28+03:00","moonset":"2023-01-31T04:56:36+03:00","moon_phase":13,"start_date":"2023-01-31T00:00:00+03:00","night":{"light":"dark","condition":"cloudy_snow_0","condition_s":"облачно, небольшой снег","temp_min":-4,"temp_max":-2,"temp":-2,"humidity":91,"prec_prob":97,"wind_gust":15,"wind_speed":6,"wind_dir":"s","pressure":737,"uvi":1,"feels_like":-10,"comf_idx":5},"day":{"light":"light","condition":"mostly-cloudy","condition_s":"облачно с прояснениями","temp_min":-4,"temp_max":-1,"temp":-1,"humidity":90,"prec_prob":20,"wind_gust":12,"wind_speed":5,"wind_dir":"s","pressure":738,"uvi":2,"feels_like":-6,"comf_idx":6}},"5":{"sunrise":"2023-02-01T08:23:33+03:00","sunset":"2023-02-01T17:02:30+03:00","moonrise":"2023-02-01T12:12:01+03:00","moonset":"2023-02-01T06:13:28+03:00","moon_phase":14,"start_date":"2023-02-01T00:00:00+03:00","night":{"light":"dark","condition":"cloudy","condition_s":"облачно","temp_min":-4,"temp_max":-2,"temp":-3,"humidity":93,"prec_prob":20,"wind_gust":12,"wind_speed":5,"wind_dir":"s","pressure":740,"uvi":0,"feels_like":-9,"comf_idx":6},"day":{"light":"light","condition":"cloudy_snow_0","condition_s":"облачно, небольшой снег","temp_min":-3,"temp_max":-1,"temp":-1,"humidity":91,"prec_prob":95,"wind_gust":7,"wind_speed":3,"wind_dir":"s","pressure":742,"uvi":1,"feels_like":-5,"comf_idx":6}},"6":{"sunrise":"2023-02-02T08:21:40+03:00","sunset":"2023-02-02T17:04:39+03:00","moonrise":"2023-02-02T12:55:09+03:00","moonset":"2023-02-02T07:18:09+03:00","moon_phase":14,"start_date":"2023-02-02T00:00:00+03:00","night":{"light":"dark","condition":"cloudy_snow_0","condition_s":"облачно, небольшой снег","temp_min":-8,"temp_max":-3,"temp":-6,"humidity":98,"prec_prob":92,"wind_gust":6,"wind_speed":2,"wind_dir":"se","pressure":741,"uvi":1,"feels_like":-11,"comf_idx":5},"day":{"light":"light","condition":"cloudy_snow_0","condition_s":"облачно, небольшой снег","temp_min":-7,"temp_max":-2,"temp":-2,"humidity":87,"prec_prob":89,"wind_gust":5,"wind_speed":2,"wind_dir":"s","pressure":741,"uvi":1,"feels_like":-5,"comf_idx":6}},"7":{"sunrise":"2023-02-03T08:19:45+03:00","sunset":"2023-02-03T17:06:48+03:00","moonrise":"2023-02-03T13:53:46+03:00","moonset":"2023-02-03T08:05:12+03:00","moon_phase":15,"start_date":"2023-02-03T00:00:00+03:00","night":{"light":"dark","condition":"cloudy_snow_1","condition_s":"облачно, снег","temp_min":-8,"temp_max":-3,"temp":-5,"humidity":97,"prec_prob":100,"wind_gust":7,"wind_speed":3,"wind_dir":"se","pressure":743,"uvi":0,"feels_like":-12,"comf_idx":5},"day":{"light":"light","condition":"partly-cloudy_snow_1","condition_s":"переменная облачность, снег","temp_min":-6,"temp_max":0,"temp":0,"humidity":91,"prec_prob":84,"wind_gust":7,"wind_speed":3,"wind_dir":"sw","pressure":745,"uvi":1,"feels_like":-4,"comf_idx":6}},"8":{"sunrise":"2023-02-04T08:17:48+03:00","sunset":"2023-02-04T17:08:58+03:00","moonrise":"2023-02-04T15:04:17+03:00","moonset":"2023-02-04T08:29:02+03:00","moon_phase":15,"start_date":"2023-02-04T00:00:00+03:00","night":{"light":"dark","condition":"partly-cloudy_snow_0","condition_s":"переменная облачность, небольшой снег","temp_min":-11,"temp_max":-5,"temp":-9,"humidity":98,"prec_prob":67,"wind_gust":5,"wind_speed":1,"wind_dir":"s","pressure":749,"uvi":1,"feels_like":-15,"comf_idx":6},"day":{"light":"light","condition":"partly-cloudy_snow_0","condition_s":"переменная облачность, небольшой снег","temp_min":-10,"temp_max":-2,"temp":-3,"humidity":93,"prec_prob":67,"wind_gust":4,"wind_speed":1,"wind_dir":"n","pressure":752,"uvi":1,"feels_like":-5,"comf_idx":7}},"9":{"sunrise":"2023-02-05T08:15:48+03:00","sunset":"2023-02-05T17:11:08+03:00","moonrise":"2023-02-05T16:17:13+03:00","moonset":"2023-02-05T08:57:02+03:00","moon_phase":16,"start_date":"2023-02-05T00:00:00+03:00","night":{"light":"dark","condition":"partly-cloudy_snow_0","condition_s":"переменная облачность, небольшой снег","temp_min":-13,"temp_max":-4,"temp":-6,"humidity":95,"prec_prob":84,"wind_gust":7,"wind_speed":3,"wind_dir":"nw","pressure":757,"uvi":1,"feels_like":-18,"comf_idx":5},"day":{"light":"light","condition":"mostly-cloudy","condition_s":"облачно с прояснениями","temp_min":-15,"temp_max":-7,"temp":-7,"humidity":90,"prec_prob":6,"wind_gust":5,"wind_speed":3,"wind_dir":"nw","pressure":759,"uvi":2,"feels_like":-11,"comf_idx":6}},"10":{"sunrise":"2023-02-06T08:13:47+03:00","sunset":"2023-02-06T17:13:18+03:00","moonrise":"2023-02-06T17:39:12+03:00","moonset":"2023-02-06T09:10:31+03:00","moon_phase":0,"start_date":"2023-02-06T00:00:00+03:00","night":{"light":"dark","condition":"mostly-cloudy","condition_s":"облачно с прояснениями","temp_min":-17,"temp_max":-12,"temp":-17,"humidity":99,"prec_prob":7,"wind_gust":2,"wind_speed":2,"wind_dir":"nw","pressure":759,"uvi":1,"feels_like":-21,"comf_idx":6},"day":{"light":"light","condition":"partly-cloudy","condition_s":"переменная облачность","temp_min":-16,"temp_max":-6,"temp":-6,"humidity":86,"prec_prob":11,"wind_gust":4,"wind_speed":2,"wind_dir":"nw","pressure":758,"uvi":2,"feels_like":-10,"comf_idx":7}},"11":{"sunrise":"2023-02-07T08:11:44+03:00","sunset":"2023-02-07T17:15:28+03:00","moonrise":"2023-02-07T18:57:27+03:00","moonset":"2023-02-07T09:19:53+03:00","moon_phase":1,"start_date":"2023-02-07T00:00:00+03:00","night":{"light":"dark","condition":"mostly-cloudy","condition_s":"облачно с прояснениями","temp_min":-13,"temp_max":-9,"temp":-11,"humidity":94,"prec_prob":12,"wind_gust":5,"wind_speed":2,"wind_dir":"w","pressure":757,"uvi":1,"feels_like":-17,"comf_idx":6},"day":{"light":"light","condition":"partly-cloudy","condition_s":"переменная облачность","temp_min":-12,"temp_max":-3,"temp":-3,"humidity":84,"prec_prob":7,"wind_gust":11,"wind_speed":3,"wind_dir":"w","pressure":757,"uvi":2,"feels_like":-7,"comf_idx":8}}},"forecast_3":{"0":{"3":{"date":"2023-01-27T15:00:00+03:00","light":"light","condition":"cloudy_snow_0","condition_s":"облачно, небольшой снег","temp_min":-4,"temp_max":-2,"temp":-2,"humidity":92,"prec_prob":66,"wind_gust":7,"wind_speed":4,"wind_dir":"sw","pressure":752,"uvi":1,"feels_like":-6,"comf_idx":5},"6":{"date":"2023-01-27T18:00:00+03:00","light":"light","condition":"cloudy_snow_0","condition_s":"облачно, небольшой снег","temp_min":-3,"temp_max":-2,"temp":-3,"humidity":96,"prec_prob":70,"wind_gust":6,"wind_speed":3,"wind_dir":"sw","pressure":752,"uvi":0,"feels_like":-7,"comf_idx":5},"9":{"date":"2023-01-27T21:00:00+03:00","light":"dark","condition":"partly-cloudy_snow_0","condition_s":"переменная облачность, небольшой снег","temp_min":-4,"temp_max":-3,"temp":-4,"humidity":97,"prec_prob":64,"wind_gust":5,"wind_speed":2,"wind_dir":"sw","pressure":753,"uvi":0,"feels_like":-7,"comf_idx":6},"sunrise":"2023-01-27T08:32:27+03:00","sunset":"2023-01-27T16:51:55+03:00","moonrise":"2023-01-27T10:49:14+03:00","moon_phase":11},"1":{"12":{"date":"2023-01-28T00:00:00+03:00","light":"dark","condition":"partly-cloudy_snow_0","condition_s":"переменная облачность, небольшой снег","temp_min":-5,"temp_max":-3,"temp":-4,"humidity":98,"prec_prob":64,"wind_gust":3,"wind_speed":1,"wind_dir":"nw","pressure":754,"uvi":0,"feels_like":-7,"comf_idx":6},"15":{"date":"2023-01-28T03:00:00+03:00","light":"dark","condition":"partly-cloudy_snow_0","condition_s":"переменная облачность, небольшой снег","temp_min":-7,"temp_max":-3,"temp":-6,"humidity":98,"prec_prob":57,"wind_gust":3,"wind_speed":1,"wind_dir":"nw","pressure":754,"uvi":0,"feels_like":-9,"comf_idx":6},"18":{"date":"2023-01-28T06:00:00+03:00","light":"dark","condition":"cloudy_snow_0","condition_s":"облачно, небольшой снег","temp_min":-7,"temp_max":-5,"temp":-6,"humidity":98,"prec_prob":62,"wind_gust":3,"wind_speed":2,"wind_dir":"ne","pressure":754,"uvi":0,"feels_like":-9,"comf_idx":5},"21":{"date":"2023-01-28T09:00:00+03:00","light":"dark","condition":"partly-cloudy_snow_0","condition_s":"переменная облачность, небольшой снег","temp_min":-8,"temp_max":-5,"temp":-7,"humidity":98,"prec_prob":62,"wind_gust":3,"wind_speed":2,"wind_dir":"ne","pressure":755,"uvi":1,"feels_like":-10,"comf_idx":6},"24":{"date":"2023-01-28T12:00:00+03:00","light":"light","condition":"partly-cloudy_snow_0","condition_s":"переменная облачность, небольшой снег","temp_min":-7,"temp_max":-4,"temp":-4,"humidity":94,"prec_prob":59,"wind_gust":2,"wind_speed":1,"wind_dir":"e","pressure":755,"uvi":1,"feels_like":-7,"comf_idx":6},"27":{"date":"2023-01-28T15:00:00+03:00","light":"light","condition":"partly-cloudy_snow_0","condition_s":"переменная облачность, небольшой снег","temp_min":-7,"temp_max":-3,"temp":-3,"humidity":92,"prec_prob":61,"wind_gust":2,"wind_speed":2,"wind_dir":"se","pressure":754,"uvi":2,"feels_like":-6,"comf_idx":6},"30":{"date":"2023-01-28T18:00:00+03:00","light":"light","condition":"cloudy_snow_0","condition_s":"облачно, небольшой снег","temp_min":-3,"temp_max":-3,"temp":-3,"humidity":93,"prec_prob":41,"wind_gust":3,"wind_speed":2,"wind_dir":"se","pressure":753,"uvi":0,"feels_like":-6,"comf_idx":6},"33":{"date":"2023-01-28T21:00:00+03:00","light":"dark","condition":"cloudy","condition_s":"облачно, без существенных осадков","temp_min":-4,"temp_max":-3,"temp":-4,"humidity":90,"prec_prob":25,"wind_gust":4,"wind_speed":2,"wind_dir":"s","pressure":753,"uvi":0,"feels_like":-7,"comf_idx":6},"sunrise":"2023-01-28T08:30:45+03:00","sunset":"2023-01-28T16:54:00+03:00","moonrise":"2023-01-28T10:58:19+03:00","moonset":"2023-01-28T00:40:44+03:00","moon_phase":12},"2":{"36":{"date":"2023-01-29T00:00:00+03:00","light":"dark","condition":"cloudy","condition_s":"облачно","temp_min":-4,"temp_max":-3,"temp":-4,"humidity":89,"prec_prob":12,"wind_gust":5,"wind_speed":3,"wind_dir":"s","pressure":752,"uvi":0,"feels_like":-8,"comf_idx":6},"39":{"date":"2023-01-29T03:00:00+03:00","light":"dark","condition":"mostly-cloudy","condition_s":"облачно с прояснениями","temp_min":-8,"temp_max":-3,"temp":-8,"humidity":96,"prec_prob":10,"wind_gust":3,"wind_speed":2,"wind_dir":"s","pressure":751,"uvi":0,"feels_like":-12,"comf_idx":6},"42":{"date":"2023-01-29T06:00:00+03:00","light":"dark","condition":"partly-cloudy","condition_s":"переменная облачность","temp_min":-11,"temp_max":-8,"temp":-11,"humidity":98,"prec_prob":5,"wind_gust":2,"wind_speed":2,"wind_dir":"s","pressure":750,"uvi":0,"feels_like":-15,"comf_idx":6},"45":{"date":"2023-01-29T09:00:00+03:00","light":"dark","condition":"mostly-cloudy","condition_s":"облачно с прояснениями","temp_min":-12,"temp_max":-8,"temp":-11,"humidity":98,"prec_prob":5,"wind_gust":4,"wind_speed":2,"wind_dir":"s","pressure":749,"uvi":1,"feels_like":-15,"comf_idx":6},"48":{"date":"2023-01-29T12:00:00+03:00","light":"light","condition":"partly-cloudy","condition_s":"переменная облачность","temp_min":-11,"temp_max":-5,"temp":-5,"humidity":90,"prec_prob":5,"wind_gust":5,"wind_speed":3,"wind_dir":"sw","pressure":748,"uvi":2,"feels_like":-10,"comf_idx":7},"51":{"date":"2023-01-29T15:00:00+03:00","light":"light","condition":"partly-cloudy","condition_s":"переменная облачность","temp_min":-11,"temp_max":-4,"temp":-4,"humidity":89,"prec_prob":5,"wind_gust":6,"wind_speed":3,"wind_dir":"s","pressure":747,"uvi":2,"feels_like":-8,"comf_idx":7},"54":{"date":"2023-01-29T18:00:00+03:00","light":"light","condition":"partly-cloudy","condition_s":"переменная облачность","temp_min":-7,"temp_max":-4,"temp":-6,"humidity":94,"prec_prob":8,"wind_gust":7,"wind_speed":3,"wind_dir":"s","pressure":746,"uvi":0,"feels_like":-11,"comf_idx":7},"57":{"date":"2023-01-29T21:00:00+03:00","light":"dark","condition":"semitransparent","condition_s":"полупрозрачная облачность","temp_min":-7,"temp_max":-6,"temp":-6,"humidity":94,"prec_prob":6,"wind_gust":8,"wind_speed":3,"wind_dir":"sw","pressure":745,"uvi":0,"feels_like":-10,"comf_idx":7},"sunrise":"2023-01-29T08:29:00+03:00","sunset":"2023-01-29T16:56:07+03:00","moonrise":"2023-01-29T11:09:13+03:00","moonset":"2023-01-29T02:07:00+03:00","moon_phase":12},"3":{"60":{"date":"2023-01-30T00:00:00+03:00","light":"dark","condition":"cloudy","condition_s":"облачно","temp_min":-6,"temp_max":-5,"temp":-5,"humidity":94,"prec_prob":13,"wind_gust":9,"wind_speed":4,"wind_dir":"s","pressure":744,"uvi":0,"feels_like":-10,"comf_idx":7},"63":{"date":"2023-01-30T03:00:00+03:00","light":"dark","condition":"cloudy_snow_0","condition_s":"облачно, небольшой снег","temp_min":-6,"temp_max":-5,"temp":-5,"humidity":94,"prec_prob":89,"wind_gust":10,"wind_speed":5,"wind_dir":"s","pressure":742,"uvi":0,"feels_like":-10,"comf_idx":5},"66":{"date":"2023-01-30T06:00:00+03:00","light":"dark","condition":"cloudy_snow_0","condition_s":"облачно, небольшой снег","temp_min":-5,"temp_max":-5,"temp":-5,"humidity":93,"prec_prob":84,"wind_gust":11,"wind_speed":5,"wind_dir":"s","pressure":741,"uvi":0,"feels_like":-10,"comf_idx":5},"69":{"date":"2023-01-30T09:00:00+03:00","light":"dark","condition":"cloudy","condition_s":"облачно, без существенных осадков","temp_min":-5,"temp_max":-5,"temp":-5,"humidity":92,"prec_prob":28,"wind_gust":13,"wind_speed":6,"wind_dir":"s","pressure":740,"uvi":1,"feels_like":-11,"comf_idx":6},"72":{"date":"2023-01-30T12:00:00+03:00","light":"light","condition":"cloudy","condition_s":"облачно, без существенных осадков","temp_min":-5,"temp_max":-3,"temp":-3,"humidity":91,"prec_prob":32,"wind_gust":14,"wind_speed":6,"wind_dir":"s","pressure":738,"uvi":1,"feels_like":-9,"comf_idx":6},"75":{"date":"2023-01-30T15:00:00+03:00","light":"light","condition":"cloudy","condition_s":"облачно, без существенных осадков","temp_min":-3,"temp_max":-2,"temp":-2,"humidity":89,"prec_prob":46,"wind_gust":14,"wind_speed":7,"wind_dir":"s","pressure":737,"uvi":1,"feels_like":-9,"comf_idx":6},"78":{"date":"2023-01-30T18:00:00+03:00","light":"light","condition":"cloudy","condition_s":"облачно, без существенных осадков","temp_min":-2,"temp_max":-2,"temp":-2,"humidity":87,"prec_prob":32,"wind_gust":14,"wind_speed":7,"wind_dir":"s","pressure":736,"uvi":0,"feels_like":-9,"comf_idx":6},"81":{"date":"2023-01-30T21:00:00+03:00","light":"dark","condition":"cloudy_snow_0","condition_s":"облачно, небольшой снег","temp_min":-2,"temp_max":-2,"temp":-2,"humidity":87,"prec_prob":56,"wind_gust":15,"wind_speed":7,"wind_dir":"s","pressure":736,"uvi":0,"feels_like":-9,"comf_idx":5},"sunrise":"2023-01-30T08:27:14+03:00","sunset":"2023-01-30T16:58:14+03:00","moonrise":"2023-01-30T11:22:48+03:00","moonset":"2023-01-30T03:33:19+03:00","moon_phase":13},"4":{"84":{"date":"2023-01-31T00:00:00+03:00","light":"dark","condition":"cloudy","condition_s":"облачно, без существенных осадков","temp_min":-2,"temp_max":-2,"temp":-2,"humidity":89,"prec_prob":36,"wind_gust":14,"wind_speed":7,"wind_dir":"s","pressure":736,"uvi":0,"feels_like":-8,"comf_idx":6},"87":{"date":"2023-01-31T03:00:00+03:00","light":"dark","condition":"cloudy_snow_0","condition_s":"облачно, небольшой снег","temp_min":-2,"temp_max":-2,"temp":-2,"humidity":91,"prec_prob":91,"wind_gust":14,"wind_speed":6,"wind_dir":"s","pressure":737,"uvi":0,"feels_like":-8,"comf_idx":5},"90":{"date":"2023-01-31T06:00:00+03:00","light":"dark","condition":"cloudy_snow_0","condition_s":"облачно, небольшой снег","temp_min":-3,"temp_max":-2,"temp":-3,"humidity":92,"prec_prob":85,"wind_gust":13,"wind_speed":6,"wind_dir":"s","pressure":737,"uvi":0,"feels_like":-9,"comf_idx":5},"93":{"date":"2023-01-31T09:00:00+03:00","light":"dark","condition":"mostly-cloudy","condition_s":"облачно с прояснениями","temp_min":-4,"temp_max":-2,"temp":-4,"humidity":93,"prec_prob":24,"wind_gust":12,"wind_speed":6,"wind_dir":"s","pressure":738,"uvi":1,"feels_like":-9,"comf_idx":6},"96":{"date":"2023-01-31T12:00:00+03:00","light":"light","condition":"mostly-cloudy","condition_s":"облачно с прояснениями","temp_min":-4,"temp_max":-2,"temp":-2,"humidity":91,"prec_prob":22,"wind_gust":12,"wind_speed":6,"wind_dir":"s","pressure":738,"uvi":2,"feels_like":-8,"comf_idx":6},"99":{"date":"2023-01-31T15:00:00+03:00","light":"light","condition":"cloudy","condition_s":"облачно, без существенных осадков","temp_min":-4,"temp_max":-1,"temp":-1,"humidity":90,"prec_prob":36,"wind_gust":10,"wind_speed":5,"wind_dir":"s","pressure":739,"uvi":1,"feels_like":-6,"comf_idx":6},"102":{"date":"2023-01-31T18:00:00+03:00","light":"light","condition":"cloudy","condition_s":"облачно, без существенных осадков","temp_min":-2,"temp_max":-1,"temp":-2,"humidity":92,"prec_prob":49,"wind_gust":11,"wind_speed":5,"wind_dir":"s","pressure":739,"uvi":0,"feels_like":-7,"comf_idx":6},"105":{"date":"2023-01-31T21:00:00+03:00","light":"dark","condition":"cloudy","condition_s":"облачно","temp_min":-2,"temp_max":-1,"temp":-2,"humidity":92,"prec_prob":28,"wind_gust":12,"wind_speed":5,"wind_dir":"s","pressure":739,"uvi":0,"feels_like":-7,"comf_idx":6},"sunrise":"2023-01-31T08:25:25+03:00","sunset":"2023-01-31T17:00:22+03:00","moonrise":"2023-01-31T11:42:28+03:00","moonset":"2023-01-31T04:56:36+03:00","moon_phase":13},"5":{"108":{"date":"2023-02-01T00:00:00+03:00","light":"dark","condition":"cloudy","condition_s":"облачно","temp_min":-2,"temp_max":-2,"temp":-2,"humidity":92,"prec_prob":9,"wind_gust":11,"wind_speed":5,"wind_dir":"s","pressure":740,"uvi":0,"feels_like":-7,"comf_idx":6},"111":{"date":"2023-02-01T03:00:00+03:00","light":"dark","condition":"cloudy","condition_s":"облачно, без существенных осадков","temp_min":-3,"temp_max":-2,"temp":-3,"humidity":93,"prec_prob":36,"wind_gust":11,"wind_speed":5,"wind_dir":"s","pressure":740,"uvi":0,"feels_like":-8,"comf_idx":6},"114":{"date":"2023-02-01T06:00:00+03:00","light":"dark","condition":"cloudy","condition_s":"облачно, без существенных осадков","temp_min":-4,"temp_max":-3,"temp":-3,"humidity":92,"prec_prob":22,"wind_gust":9,"wind_speed":4,"wind_dir":"sw","pressure":741,"uvi":0,"feels_like":-8,"comf_idx":6},"117":{"date":"2023-02-01T09:00:00+03:00","light":"dark","condition":"cloudy","condition_s":"облачно, без существенных осадков","temp_min":-4,"temp_max":-2,"temp":-3,"humidity":93,"prec_prob":41,"wind_gust":8,"wind_speed":4,"wind_dir":"s","pressure":742,"uvi":0,"feels_like":-7,"comf_idx":6},"120":{"date":"2023-02-01T12:00:00+03:00","light":"light","condition":"cloudy","condition_s":"облачно, без существенных осадков","temp_min":-3,"temp_max":-1,"temp":-1,"humidity":91,"prec_prob":27,"wind_gust":7,"wind_speed":4,"wind_dir":"s","pressure":742,"uvi":1,"feels_like":-6,"comf_idx":6},"123":{"date":"2023-02-01T15:00:00+03:00","light":"light","condition":"cloudy_snow_0","condition_s":"облачно, небольшой снег","temp_min":-1,"temp_max":-1,"temp":-1,"humidity":91,"prec_prob":70,"wind_gust":6,"wind_speed":3,"wind_dir":"s","pressure":742,"uvi":1,"feels_like":-5,"comf_idx":6},"126":{"date":"2023-02-01T18:00:00+03:00","light":"light","condition":"cloudy_snow_0","condition_s":"облачно, небольшой снег","temp_min":-3,"temp_max":-1,"temp":-3,"humidity":95,"prec_prob":61,"wind_gust":5,"wind_speed":3,"wind_dir":"s","pressure":742,"uvi":0,"feels_like":-6,"comf_idx":6},"129":{"date":"2023-02-01T21:00:00+03:00","light":"dark","condition":"cloudy","condition_s":"облачно, без существенных осадков","temp_min":-3,"temp_max":-3,"temp":-3,"humidity":95,"prec_prob":42,"wind_gust":5,"wind_speed":2,"wind_dir":"s","pressure":742,"uvi":0,"feels_like":-7,"comf_idx":6},"sunrise":"2023-02-01T08:23:33+03:00","sunset":"2023-02-01T17:02:30+03:00","moonrise":"2023-02-01T12:12:01+03:00","moonset":"2023-02-01T06:13:28+03:00","moon_phase":14},"6":{"132":{"date":"2023-02-02T00:00:00+03:00","light":"dark","condition":"cloudy","condition_s":"облачно, без существенных осадков","temp_min":-4,"temp_max":-3,"temp":-4,"humidity":96,"prec_prob":42,"wind_gust":6,"wind_speed":2,"wind_dir":"s","pressure":741,"uvi":0,"feels_like":-7,"comf_idx":6},"135":{"date":"2023-02-02T03:00:00+03:00","light":"dark","condition":"cloudy","condition_s":"облачно","temp_min":-6,"temp_max":-3,"temp":-6,"humidity":98,"prec_prob":11,"wind_gust":3,"wind_speed":2,"wind_dir":"se","pressure":741,"uvi":0,"feels_like":-10,"comf_idx":6},"138":{"date":"2023-02-02T06:00:00+03:00","light":"dark","condition":"cloudy_snow_0","condition_s":"облачно, небольшой снег","temp_min":-7,"temp_max":-6,"temp":-6,"humidity":98,"prec_prob":58,"wind_gust":3,"wind_speed":2,"wind_dir":"se","pressure":741,"uvi":0,"feels_like":-10,"comf_idx":5},"141":{"date":"2023-02-02T09:00:00+03:00","light":"dark","condition":"cloudy_snow_0","condition_s":"облачно, небольшой снег","temp_min":-8,"temp_max":-6,"temp":-7,"humidity":99,"prec_prob":36,"wind_gust":2,"wind_speed":2,"wind_dir":"se","pressure":741,"uvi":1,"feels_like":-10,"comf_idx":6},"144":{"date":"2023-02-02T12:00:00+03:00","light":"light","condition":"cloudy","condition_s":"облачно, без существенных осадков","temp_min":-7,"temp_max":-3,"temp":-3,"humidity":93,"prec_prob":45,"wind_gust":3,"wind_speed":2,"wind_dir":"s","pressure":741,"uvi":1,"feels_like":-6,"comf_idx":6},"147":{"date":"2023-02-02T15:00:00+03:00","light":"light","condition":"cloudy_snow_0","condition_s":"облачно, небольшой снег","temp_min":-7,"temp_max":-2,"temp":-2,"humidity":87,"prec_prob":57,"wind_gust":3,"wind_speed":2,"wind_dir":"s","pressure":741,"uvi":1,"feels_like":-5,"comf_idx":6},"150":{"date":"2023-02-02T18:00:00+03:00","light":"light","condition":"cloudy","condition_s":"облачно, без существенных осадков","temp_min":-5,"temp_max":-2,"temp":-5,"humidity":93,"prec_prob":50,"wind_gust":4,"wind_speed":2,"wind_dir":"se","pressure":742,"uvi":0,"feels_like":-8,"comf_idx":6},"153":{"date":"2023-02-02T21:00:00+03:00","light":"dark","condition":"cloudy","condition_s":"облачно","temp_min":-8,"temp_max":-5,"temp":-7,"humidity":96,"prec_prob":8,"wind_gust":5,"wind_speed":2,"wind_dir":"se","pressure":743,"uvi":0,"feels_like":-11,"comf_idx":7},"sunrise":"2023-02-02T08:21:40+03:00","sunset":"2023-02-02T17:04:39+03:00","moonrise":"2023-02-02T12:55:09+03:00","moonset":"2023-02-02T07:18:09+03:00","moon_phase":14},"7":{"156":{"date":"2023-02-03T00:00:00+03:00","light":"dark","condition":"partly-cloudy","condition_s":"переменная облачность","temp_min":-8,"temp_max":-6,"temp":-6,"humidity":97,"prec_prob":19,"wind_gust":6,"wind_speed":2,"wind_dir":"se","pressure":743,"uvi":0,"feels_like":-10,"comf_idx":7},"159":{"date":"2023-02-03T03:00:00+03:00","light":"dark","condition":"cloudy_snow_0","condition_s":"облачно, небольшой снег","temp_min":-8,"temp_max":-5,"temp":-5,"humidity":97,"prec_prob":86,"wind_gust":7,"wind_speed":3,"wind_dir":"se","pressure":743,"uvi":0,"feels_like":-9,"comf_idx":6},"162":{"date":"2023-02-03T06:00:00+03:00","light":"dark","condition":"cloudy_snow_0","condition_s":"облачно, небольшой снег","temp_min":-5,"temp_max":-4,"temp":-4,"humidity":97,"prec_prob":93,"wind_gust":6,"wind_speed":3,"wind_dir":"se","pressure":743,"uvi":0,"feels_like":-8,"comf_idx":6},"165":{"date":"2023-02-03T09:00:00+03:00","light":"dark","condition":"cloudy_snow_1","condition_s":"облачно, снег","temp_min":-4,"temp_max":-3,"temp":-3,"humidity":97,"prec_prob":99,"wind_gust":6,"wind_speed":3,"wind_dir":"se","pressure":743,"uvi":0,"feels_like":-7,"comf_idx":5},"168":{"date":"2023-02-03T12:00:00+03:00","light":"light","condition":"cloudy_snow_1","condition_s":"облачно, снег","temp_min":-3,"temp_max":-1,"temp":-1,"humidity":96,"prec_prob":100,"wind_gust":6,"wind_speed":3,"wind_dir":"s","pressure":744,"uvi":1,"feels_like":-5,"comf_idx":5},"171":{"date":"2023-02-03T15:00:00+03:00","light":"light","condition":"cloudy_snow_0","condition_s":"облачно, небольшой снег","temp_min":-1,"temp_max":0,"temp":0,"humidity":91,"prec_prob":93,"wind_gust":7,"wind_speed":3,"wind_dir":"sw","pressure":745,"uvi":1,"feels_like":-4,"comf_idx":6},"174":{"date":"2023-02-03T18:00:00+03:00","light":"light","condition":"partly-cloudy","condition_s":"переменная облачность","temp_min":-5,"temp_max":0,"temp":-5,"humidity":95,"prec_prob":24,"wind_gust":5,"wind_speed":3,"wind_dir":"s","pressure":746,"uvi":0,"feels_like":-8,"comf_idx":7},"177":{"date":"2023-02-03T21:00:00+03:00","light":"dark","condition":"partly-cloudy","condition_s":"переменная облачность","temp_min":-6,"temp_max":0,"temp":-5,"humidity":96,"prec_prob":5,"wind_gust":5,"wind_speed":3,"wind_dir":"s","pressure":748,"uvi":0,"feels_like":-9,"comf_idx":7},"sunrise":"2023-02-03T08:19:45+03:00","sunset":"2023-02-03T17:06:48+03:00","moonrise":"2023-02-03T13:53:46+03:00","moonset":"2023-02-03T08:05:12+03:00","moon_phase":15},"8":{"180":{"date":"2023-02-04T00:00:00+03:00","light":"dark","condition":"mostly-cloudy","condition_s":"облачно с прояснениями","temp_min":-6,"temp_max":-5,"temp":-6,"humidity":97,"prec_prob":10,"wind_gust":4,"wind_speed":2,"wind_dir":"s","pressure":749,"uvi":0,"feels_like":-9,"comf_idx":6},"183":{"date":"2023-02-04T03:00:00+03:00","light":"dark","condition":"mostly-cloudy","condition_s":"облачно с прояснениями","temp_min":-9,"temp_max":-5,"temp":-9,"humidity":98,"prec_prob":9,"wind_gust":1,"wind_speed":1,"wind_dir":"s","pressure":750,"uvi":0,"feels_like":-13,"comf_idx":6},"186":{"date":"2023-02-04T06:00:00+03:00","light":"dark","condition":"partly-cloudy","condition_s":"переменная облачность","temp_min":-11,"temp_max":-9,"temp":-11,"humidity":99,"prec_prob":5,"wind_gust":1,"wind_speed":1,"wind_dir":"se","pressure":750,"uvi":0,"feels_like":-15,"comf_idx":6},"189":{"date":"2023-02-04T09:00:00+03:00","light":"dark","condition":"partly-cloudy_snow_0","condition_s":"переменная облачность, небольшой снег","temp_min":-12,"temp_max":-9,"temp":-10,"humidity":98,"prec_prob":55,"wind_gust":0,"wind_speed":0,"wind_dir":"e","pressure":751,"uvi":1,"feels_like":-12,"comf_idx":6},"192":{"date":"2023-02-04T12:00:00+03:00","light":"light","condition":"mostly-cloudy","condition_s":"облачно с прояснениями","temp_min":-10,"temp_max":-4,"temp":-4,"humidity":93,"prec_prob":5,"wind_gust":1,"wind_speed":1,"wind_dir":"se","pressure":752,"uvi":1,"feels_like":-7,"comf_idx":7},"195":{"date":"2023-02-04T15:00:00+03:00","light":"light","condition":"partly-cloudy","condition_s":"переменная облачность","temp_min":-10,"temp_max":-3,"temp":-3,"humidity":93,"prec_prob":7,"wind_gust":2,"wind_speed":1,"wind_dir":"n","pressure":752,"uvi":1,"feels_like":-5,"comf_idx":7},"198":{"date":"2023-02-04T18:00:00+03:00","light":"light","condition":"partly-cloudy","condition_s":"переменная облачность","temp_min":-7,"temp_max":-3,"temp":-6,"humidity":95,"prec_prob":5,"wind_gust":2,"wind_speed":2,"wind_dir":"n","pressure":754,"uvi":0,"feels_like":-10,"comf_idx":7},"201":{"date":"2023-02-04T21:00:00+03:00","light":"dark","condition":"partly-cloudy_snow_0","condition_s":"переменная облачность, небольшой снег","temp_min":-7,"temp_max":-3,"temp":-5,"humidity":96,"prec_prob":61,"wind_gust":4,"wind_speed":2,"wind_dir":"n","pressure":755,"uvi":0,"feels_like":-8,"comf_idx":6},"sunrise":"2023-02-04T08:17:48+03:00","sunset":"2023-02-04T17:08:58+03:00","moonrise":"2023-02-04T15:04:17+03:00","moonset":"2023-02-04T08:29:02+03:00","moon_phase":15},"9":{"204":{"date":"2023-02-05T00:00:00+03:00","light":"dark","condition":"cloudy_snow_0","condition_s":"облачно, небольшой снег","temp_min":-5,"temp_max":-4,"temp":-4,"humidity":95,"prec_prob":42,"wind_gust":5,"wind_speed":2,"wind_dir":"n","pressure":756,"uvi":0,"feels_like":-8,"comf_idx":5},"207":{"date":"2023-02-05T03:00:00+03:00","light":"dark","condition":"cloudy","condition_s":"облачно","temp_min":-7,"temp_max":-4,"temp":-6,"humidity":95,"prec_prob":21,"wind_gust":6,"wind_speed":3,"wind_dir":"nw","pressure":757,"uvi":0,"feels_like":-10,"comf_idx":6},"210":{"date":"2023-02-05T06:00:00+03:00","light":"dark","condition":"mostly-cloudy","condition_s":"облачно с прояснениями","temp_min":-12,"temp_max":-6,"temp":-12,"humidity":97,"prec_prob":5,"wind_gust":6,"wind_speed":3,"wind_dir":"nw","pressure":758,"uvi":0,"feels_like":-16,"comf_idx":6},"213":{"date":"2023-02-05T09:00:00+03:00","light":"dark","condition":"partly-cloudy","condition_s":"переменная облачность","temp_min":-14,"temp_max":-12,"temp":-13,"humidity":97,"prec_prob":5,"wind_gust":7,"wind_speed":3,"wind_dir":"n","pressure":759,"uvi":1,"feels_like":-18,"comf_idx":6},"216":{"date":"2023-02-05T12:00:00+03:00","light":"light","condition":"partly-cloudy","condition_s":"переменная облачность","temp_min":-13,"temp_max":-9,"temp":-9,"humidity":91,"prec_prob":5,"wind_gust":3,"wind_speed":2,"wind_dir":"n","pressure":759,"uvi":2,"feels_like":-13,"comf_idx":7},"219":{"date":"2023-02-05T15:00:00+03:00","light":"light","condition":"cloudy","condition_s":"облачно","temp_min":-13,"temp_max":-7,"temp":-7,"humidity":90,"prec_prob":10,"wind_gust":5,"wind_speed":3,"wind_dir":"nw","pressure":759,"uvi":2,"feels_like":-11,"comf_idx":6},"222":{"date":"2023-02-05T18:00:00+03:00","light":"light","condition":"mostly-cloudy","condition_s":"облачно с прояснениями","temp_min":-12,"temp_max":-7,"temp":-12,"humidity":98,"prec_prob":5,"wind_gust":2,"wind_speed":2,"wind_dir":"nw","pressure":759,"uvi":0,"feels_like":-16,"comf_idx":6},"225":{"date":"2023-02-05T21:00:00+03:00","light":"dark","condition":"mostly-cloudy","condition_s":"облачно с прояснениями","temp_min":-15,"temp_max":-12,"temp":-15,"humidity":99,"prec_prob":5,"wind_gust":2,"wind_speed":2,"wind_dir":"n","pressure":760,"uvi":0,"feels_like":-19,"comf_idx":6},"sunrise":"2023-02-05T08:15:48+03:00","sunset":"2023-02-05T17:11:08+03:00","moonrise":"2023-02-05T16:17:13+03:00","moonset":"2023-02-05T08:57:02+03:00","moon_phase":16},"10":{"228":{"date":"2023-02-06T00:00:00+03:00","light":"dark","condition":"mostly-cloudy","condition_s":"облачно с прояснениями","temp_min":-16,"temp_max":-15,"temp":-16,"humidity":99,"prec_prob":5,"wind_gust":2,"wind_speed":2,"wind_dir":"nw","pressure":759,"uvi":0,"feels_like":-20,"comf_idx":6},"231":{"date":"2023-02-06T03:00:00+03:00","light":"dark","condition":"mostly-cloudy","condition_s":"облачно с прояснениями","temp_min":-17,"temp_max":-15,"temp":-17,"humidity":99,"prec_prob":5,"wind_gust":2,"wind_speed":2,"wind_dir":"nw","pressure":759,"uvi":0,"feels_like":-21,"comf_idx":6},"234":{"date":"2023-02-06T06:00:00+03:00","light":"dark","condition":"cloudy","condition_s":"облачно","temp_min":-17,"temp_max":-16,"temp":-16,"humidity":99,"prec_prob":10,"wind_gust":1,"wind_speed":1,"wind_dir":"nw","pressure":759,"uvi":0,"feels_like":-20,"comf_idx":6},"237":{"date":"2023-02-06T09:00:00+03:00","light":"dark","condition":"mostly-cloudy","condition_s":"облачно с прояснениями","temp_min":-17,"temp_max":-15,"temp":-16,"humidity":98,"prec_prob":5,"wind_gust":2,"wind_speed":2,"wind_dir":"nw","pressure":759,"uvi":1,"feels_like":-20,"comf_idx":6},"240":{"date":"2023-02-06T12:00:00+03:00","light":"light","condition":"partly-cloudy","condition_s":"переменная облачность","temp_min":-16,"temp_max":-9,"temp":-9,"humidity":90,"prec_prob":5,"wind_gust":2,"wind_speed":1,"wind_dir":"nw","pressure":759,"uvi":2,"feels_like":-12,"comf_idx":7},"243":{"date":"2023-02-06T15:00:00+03:00","light":"light","condition":"partly-cloudy","condition_s":"переменная облачность","temp_min":-9,"temp_max":-6,"temp":-6,"humidity":86,"prec_prob":5,"wind_gust":4,"wind_speed":2,"wind_dir":"nw","pressure":758,"uvi":2,"feels_like":-10,"comf_idx":7},"246":{"date":"2023-02-06T18:00:00+03:00","light":"light","condition":"mainly-clear","condition_s":"малооблачно","temp_min":-11,"temp_max":-6,"temp":-11,"humidity":96,"prec_prob":14,"wind_gust":2,"wind_speed":2,"wind_dir":"w","pressure":758,"uvi":0,"feels_like":-15,"comf_idx":7},"249":{"date":"2023-02-06T21:00:00+03:00","light":"dark","condition":"mostly-cloudy","condition_s":"облачно с прояснениями","temp_min":-12,"temp_max":-11,"temp":-11,"humidity":95,"prec_prob":29,"wind_gust":2,"wind_speed":2,"wind_dir":"w","pressure":757,"uvi":0,"feels_like":-15,"comf_idx":6},"sunrise":"2023-02-06T08:13:47+03:00","sunset":"2023-02-06T17:13:18+03:00","moonrise":"2023-02-06T17:39:12+03:00","moonset":"2023-02-06T09:10:31+03:00","moon_phase":0},"11":{"252":{"date":"2023-02-07T00:00:00+03:00","light":"dark","condition":"mostly-cloudy","condition_s":"облачно с прояснениями","temp_min":-11,"temp_max":-9,"temp":-10,"humidity":94,"prec_prob":5,"wind_gust":2,"wind_speed":2,"wind_dir":"w","pressure":757,"uvi":0,"feels_like":-14,"comf_idx":6},"255":{"date":"2023-02-07T03:00:00+03:00","light":"dark","condition":"mostly-cloudy","condition_s":"облачно с прояснениями","temp_min":-12,"temp_max":-9,"temp":-11,"humidity":94,"prec_prob":5,"wind_gust":4,"wind_speed":2,"wind_dir":"w","pressure":757,"uvi":0,"feels_like":-15,"comf_idx":6},"261":{"date":"2023-02-07T09:00:00+03:00","light":"dark","condition":"mainly-clear","condition_s":"малооблачно","temp_min":-13,"temp_max":-11,"temp":-12,"humidity":93,"prec_prob":17,"wind_gust":5,"wind_speed":2,"wind_dir":"w","pressure":757,"uvi":1,"feels_like":-16,"comf_idx":7},"sunrise":"2023-02-07T08:11:44+03:00","sunset":"2023-02-07T17:15:28+03:00","moonrise":"2023-02-07T18:57:27+03:00","moonset":"2023-02-07T09:19:53+03:00","moon_phase":1},"start_date":"2023-01-27T12:00:00+03:00"},"forecast_1":{"0":{"1":{"date":"2023-01-27T15:00:00+03:00","light":"light","condition":"cloudy_snow_0","condition_s":"облачно, небольшой снег","temp_min":-4,"temp_max":-2,"temp":-2,"humidity":92,"prec_prob":66,"wind_gust":7,"wind_speed":4,"wind_dir":"sw","pressure":752,"uvi":1,"feels_like":-6,"comf_idx":5},"2":{"date":"2023-01-27T16:00:00+03:00","light":"light","condition":"cloudy_snow_0","condition_s":"облачно, небольшой снег","temp_min":-4,"temp_max":-2,"temp":-2,"humidity":94,"prec_prob":70,"wind_gust":6,"wind_speed":3,"wind_dir":"sw","pressure":752,"uvi":1,"feels_like":-6,"comf_idx":4},"3":{"date":"2023-01-27T17:00:00+03:00","light":"dark","condition":"cloudy_snow_0","condition_s":"облачно, небольшой снег","temp_min":-3,"temp_max":-2,"temp":-3,"humidity":95,"prec_prob":70,"wind_gust":6,"wind_speed":3,"wind_dir":"sw","pressure":752,"uvi":0,"feels_like":-6,"comf_idx":4},"4":{"date":"2023-01-27T18:00:00+03:00","light":"dark","condition":"cloudy_snow_0","condition_s":"облачно, небольшой снег","temp_min":-3,"temp_max":-2,"temp":-3,"humidity":96,"prec_prob":70,"wind_gust":6,"wind_speed":3,"wind_dir":"sw","pressure":752,"uvi":0,"feels_like":-7,"comf_idx":5},"5":{"date":"2023-01-27T19:00:00+03:00","light":"dark","condition":"partly-cloudy_snow_0","condition_s":"переменная облачность, небольшой снег","temp_min":-4,"temp_max":-2,"temp":-3,"humidity":96,"prec_prob":64,"wind_gust":5,"wind_speed":3,"wind_dir":"sw","pressure":752,"uvi":0,"feels_like":-7,"comf_idx":4},"6":{"date":"2023-01-27T20:00:00+03:00","light":"dark","condition":"partly-cloudy_snow_0","condition_s":"переменная облачность, небольшой снег","temp_min":-4,"temp_max":-3,"temp":-4,"humidity":97,"prec_prob":64,"wind_gust":5,"wind_speed":2,"wind_dir":"sw","pressure":753,"uvi":0,"feels_like":-7,"comf_idx":5},"7":{"date":"2023-01-27T21:00:00+03:00","light":"dark","condition":"partly-cloudy_snow_0","condition_s":"переменная облачность, небольшой снег","temp_min":-4,"temp_max":-3,"temp":-4,"humidity":97,"prec_prob":64,"wind_gust":5,"wind_speed":2,"wind_dir":"sw","pressure":753,"uvi":0,"feels_like":-7,"comf_idx":6},"8":{"date":"2023-01-27T22:00:00+03:00","light":"dark","condition":"partly-cloudy_snow_0","condition_s":"переменная облачность, небольшой снег","temp_min":-4,"temp_max":-3,"temp":-4,"humidity":97,"prec_prob":64,"wind_gust":3,"wind_speed":2,"wind_dir":"nw","pressure":753,"uvi":0,"feels_like":-7,"comf_idx":5},"9":{"date":"2023-01-27T23:00:00+03:00","light":"dark","condition":"partly-cloudy_snow_0","condition_s":"переменная облачность, небольшой снег","temp_min":-5,"temp_max":-3,"temp":-4,"humidity":97,"prec_prob":64,"wind_gust":3,"wind_speed":2,"wind_dir":"nw","pressure":753,"uvi":0,"feels_like":-8,"comf_idx":5},"sunrise":"2023-01-27T08:32:27+03:00","sunset":"2023-01-27T16:51:55+03:00","moonrise":"2023-01-27T10:49:14+03:00","moon_phase":11},"1":{"10":{"date":"2023-01-28T00:00:00+03:00","light":"dark","condition":"partly-cloudy_snow_0","condition_s":"переменная облачность, небольшой снег","temp_min":-5,"temp_max":-3,"temp":-4,"humidity":98,"prec_prob":64,"wind_gust":3,"wind_speed":1,"wind_dir":"nw","pressure":754,"uvi":0,"feels_like":-7,"comf_idx":6},"11":{"date":"2023-01-28T01:00:00+03:00","light":"dark","condition":"partly-cloudy_snow_0","condition_s":"переменная облачность, небольшой снег","temp_min":-6,"temp_max":-3,"temp":-5,"humidity":98,"prec_prob":57,"wind_gust":3,"wind_speed":1,"wind_dir":"nw","pressure":754,"uvi":0,"feels_like":-8,"comf_idx":5},"12":{"date":"2023-01-28T02:00:00+03:00","light":"dark","condition":"partly-cloudy_snow_0","condition_s":"переменная облачность, небольшой снег","temp_min":-6,"temp_max":-3,"temp":-5,"humidity":98,"prec_prob":57,"wind_gust":3,"wind_speed":1,"wind_dir":"nw","pressure":754,"uvi":0,"feels_like":-8,"comf_idx":5},"13":{"date":"2023-01-28T03:00:00+03:00","light":"dark","condition":"partly-cloudy_snow_0","condition_s":"переменная облачность, небольшой снег","temp_min":-7,"temp_max":-3,"temp":-6,"humidity":98,"prec_prob":57,"wind_gust":3,"wind_speed":1,"wind_dir":"nw","pressure":754,"uvi":0,"feels_like":-9,"comf_idx":6},"14":{"date":"2023-01-28T04:00:00+03:00","light":"dark","condition":"cloudy_snow_0","condition_s":"облачно, небольшой снег","temp_min":-7,"temp_max":-4,"temp":-6,"humidity":98,"prec_prob":62,"wind_gust":3,"wind_speed":1,"wind_dir":"ne","pressure":754,"uvi":0,"feels_like":-9,"comf_idx":4},"15":{"date":"2023-01-28T05:00:00+03:00","light":"dark","condition":"cloudy_snow_0","condition_s":"облачно, небольшой снег","temp_min":-7,"temp_max":-4,"temp":-6,"humidity":98,"prec_prob":62,"wind_gust":3,"wind_speed":2,"wind_dir":"ne","pressure":754,"uvi":0,"feels_like":-9,"comf_idx":4},"16":{"date":"2023-01-28T06:00:00+03:00","light":"dark","condition":"cloudy_snow_0","condition_s":"облачно, небольшой снег","temp_min":-7,"temp_max":-5,"temp":-6,"humidity":98,"prec_prob":62,"wind_gust":3,"wind_speed":2,"wind_dir":"ne","pressure":754,"uvi":0,"feels_like":-9,"comf_idx":5},"17":{"date":"2023-01-28T07:00:00+03:00","light":"dark","condition":"partly-cloudy_snow_0","condition_s":"переменная облачность, небольшой снег","temp_min":-7,"temp_max":-5,"temp":-6,"humidity":98,"prec_prob":62,"wind_gust":3,"wind_speed":2,"wind_dir":"ne","pressure":754,"uvi":0,"feels_like":-10,"comf_idx":4},"18":{"date":"2023-01-28T08:00:00+03:00","light":"dark","condition":"partly-cloudy_snow_0","condition_s":"переменная облачность, небольшой снег","temp_min":-8,"temp_max":-5,"temp":-7,"humidity":98,"prec_prob":62,"wind_gust":3,"wind_speed":2,"wind_dir":"ne","pressure":754,"uvi":0,"feels_like":-10,"comf_idx":4},"19":{"date":"2023-01-28T09:00:00+03:00","light":"light","condition":"partly-cloudy_snow_0","condition_s":"переменная облачность, небольшой снег","temp_min":-8,"temp_max":-5,"temp":-7,"humidity":98,"prec_prob":62,"wind_gust":3,"wind_speed":2,"wind_dir":"ne","pressure":755,"uvi":1,"feels_like":-10,"comf_idx":6},"20":{"date":"2023-01-28T10:00:00+03:00","light":"light","condition":"partly-cloudy_snow_0","condition_s":"переменная облачность, небольшой снег","temp_min":-8,"temp_max":-4,"temp":-6,"humidity":96,"prec_prob":59,"wind_gust":2,"wind_speed":2,"wind_dir":"e","pressure":755,"uvi":1,"feels_like":-9,"comf_idx":4},"21":{"date":"2023-01-28T11:00:00+03:00","light":"light","condition":"partly-cloudy_snow_0","condition_s":"переменная облачность, небольшой снег","temp_min":-7,"temp_max":-4,"temp":-5,"humidity":95,"prec_prob":59,"wind_gust":2,"wind_speed":1,"wind_dir":"e","pressure":755,"uvi":1,"feels_like":-8,"comf_idx":5},"22":{"date":"2023-01-28T12:00:00+03:00","light":"light","condition":"partly-cloudy_snow_0","condition_s":"переменная облачность, небольшой снег","temp_min":-7,"temp_max":-4,"temp":-4,"humidity":94,"prec_prob":59,"wind_gust":2,"wind_speed":1,"wind_dir":"e","pressure":755,"uvi":1,"feels_like":-7,"comf_idx":6},"23":{"date":"2023-01-28T13:00:00+03:00","light":"light","condition":"partly-cloudy_snow_0","condition_s":"переменная облачность, небольшой снег","temp_min":-7,"temp_max":-3,"temp":-4,"humidity":93,"prec_prob":61,"wind_gust":2,"wind_speed":2,"wind_dir":"se","pressure":755,"uvi":2,"feels_like":-7,"comf_idx":5},"24":{"date":"2023-01-28T14:00:00+03:00","light":"light","condition":"partly-cloudy_snow_0","condition_s":"переменная облачность, небольшой снег","temp_min":-7,"temp_max":-3,"temp":-3,"humidity":93,"prec_prob":61,"wind_gust":2,"wind_speed":2,"wind_dir":"se","pressure":754,"uvi":1,"feels_like":-6,"comf_idx":5},"25":{"date":"2023-01-28T15:00:00+03:00","light":"light","condition":"partly-cloudy_snow_0","condition_s":"переменная облачность, небольшой снег","temp_min":-7,"temp_max":-3,"temp":-3,"humidity":92,"prec_prob":61,"wind_gust":2,"wind_speed":2,"wind_dir":"se","pressure":754,"uvi":1,"feels_like":-6,"comf_idx":6},"26":{"date":"2023-01-28T16:00:00+03:00","light":"light","condition":"cloudy_snow_0","condition_s":"облачно, небольшой снег","temp_min":-6,"temp_max":-3,"temp":-3,"humidity":92,"prec_prob":41,"wind_gust":3,"wind_speed":2,"wind_dir":"se","pressure":754,"uvi":1,"feels_like":-6,"comf_idx":4},"27":{"date":"2023-01-28T17:00:00+03:00","light":"dark","condition":"cloudy_snow_0","condition_s":"облачно, небольшой снег","temp_min":-5,"temp_max":-3,"temp":-3,"humidity":93,"prec_prob":41,"wind_gust":3,"wind_speed":2,"wind_dir":"se","pressure":754,"uvi":0,"feels_like":-6,"comf_idx":4},"28":{"date":"2023-01-28T18:00:00+03:00","light":"dark","condition":"cloudy_snow_0","condition_s":"облачно, небольшой снег","temp_min":-3,"temp_max":-3,"temp":-3,"humidity":93,"prec_prob":41,"wind_gust":3,"wind_speed":2,"wind_dir":"se","pressure":753,"uvi":0,"feels_like":-6,"comf_idx":6},"29":{"date":"2023-01-28T19:00:00+03:00","light":"dark","condition":"cloudy","condition_s":"облачно, без существенных осадков","temp_min":-4,"temp_max":-3,"temp":-3,"humidity":92,"prec_prob":25,"wind_gust":4,"wind_speed":2,"wind_dir":"s","pressure":753,"uvi":0,"feels_like":-7,"comf_idx":4},"30":{"date":"2023-01-28T20:00:00+03:00","light":"dark","condition":"cloudy","condition_s":"облачно, без существенных осадков","temp_min":-4,"temp_max":-3,"temp":-3,"humidity":91,"prec_prob":25,"wind_gust":4,"wind_speed":2,"wind_dir":"s","pressure":753,"uvi":0,"feels_like":-7,"comf_idx":4},"31":{"date":"2023-01-28T21:00:00+03:00","light":"dark","condition":"cloudy","condition_s":"облачно, без существенных осадков","temp_min":-4,"temp_max":-3,"temp":-4,"humidity":90,"prec_prob":25,"wind_gust":4,"wind_speed":2,"wind_dir":"s","pressure":753,"uvi":0,"feels_like":-7,"comf_idx":6},"32":{"date":"2023-01-28T22:00:00+03:00","light":"dark","condition":"cloudy","condition_s":"облачно","temp_min":-4,"temp_max":-3,"temp":-4,"humidity":90,"prec_prob":12,"wind_gust":5,"wind_speed":2,"wind_dir":"s","pressure":753,"uvi":0,"feels_like":-7,"comf_idx":5},"33":{"date":"2023-01-28T23:00:00+03:00","light":"dark","condition":"cloudy","condition_s":"облачно","temp_min":-4,"temp_max":-3,"temp":-4,"humidity":89,"prec_prob":12,"wind_gust":5,"wind_speed":3,"wind_dir":"s","pressure":753,"uvi":0,"feels_like":-8,"comf_idx":5},"sunrise":"2023-01-28T08:30:45+03:00","sunset":"2023-01-28T16:54:00+03:00","moonrise":"2023-01-28T10:58:19+03:00","moonset":"2023-01-28T00:40:44+03:00","moon_phase":12},"2":{"34":{"date":"2023-01-29T00:00:00+03:00","light":"dark","condition":"cloudy","condition_s":"облачно","temp_min":-4,"temp_max":-3,"temp":-4,"humidity":89,"prec_prob":12,"wind_gust":5,"wind_speed":3,"wind_dir":"s","pressure":752,"uvi":0,"feels_like":-8,"comf_idx":6},"35":{"date":"2023-01-29T01:00:00+03:00","light":"dark","condition":"mostly-cloudy","condition_s":"облачно с прояснениями","temp_min":-5,"temp_max":-3,"temp":-5,"humidity":91,"prec_prob":10,"wind_gust":3,"wind_speed":2,"wind_dir":"s","pressure":752,"uvi":0,"feels_like":-9,"comf_idx":5},"36":{"date":"2023-01-29T02:00:00+03:00","light":"dark","condition":"mostly-cloudy","condition_s":"облачно с прояснениями","temp_min":-7,"temp_max":-3,"temp":-7,"humidity":94,"prec_prob":10,"wind_gust":3,"wind_speed":2,"wind_dir":"s","pressure":752,"uvi":0,"feels_like":-10,"comf_idx":5},"37":{"date":"2023-01-29T03:00:00+03:00","light":"dark","condition":"mostly-cloudy","condition_s":"облачно с прояснениями","temp_min":-8,"temp_max":-3,"temp":-8,"humidity":96,"prec_prob":10,"wind_gust":3,"wind_speed":2,"wind_dir":"s","pressure":751,"uvi":0,"feels_like":-12,"comf_idx":6},"38":{"date":"2023-01-29T04:00:00+03:00","light":"dark","condition":"partly-cloudy","condition_s":"переменная облачность","temp_min":-9,"temp_max":-5,"temp":-9,"humidity":97,"prec_prob":5,"wind_gust":2,"wind_speed":2,"wind_dir":"s","pressure":751,"uvi":0,"feels_like":-13,"comf_idx":5},"39":{"date":"2023-01-29T05:00:00+03:00","light":"dark","condition":"partly-cloudy","condition_s":"переменная облачность","temp_min":-10,"temp_max":-7,"temp":-10,"humidity":97,"prec_prob":5,"wind_gust":2,"wind_speed":2,"wind_dir":"s","pressure":750,"uvi":0,"feels_like":-14,"comf_idx":5},"40":{"date":"2023-01-29T06:00:00+03:00","light":"dark","condition":"partly-cloudy","condition_s":"переменная облачность","temp_min":-11,"temp_max":-8,"temp":-11,"humidity":98,"prec_prob":5,"wind_gust":2,"wind_speed":2,"wind_dir":"s","pressure":750,"uvi":0,"feels_like":-15,"comf_idx":6},"41":{"date":"2023-01-29T07:00:00+03:00","light":"dark","condition":"mostly-cloudy","condition_s":"облачно с прояснениями","temp_min":-11,"temp_max":-8,"temp":-11,"humidity":98,"prec_prob":5,"wind_gust":4,"wind_speed":2,"wind_dir":"s","pressure":750,"uvi":0,"feels_like":-15,"comf_idx":5},"42":{"date":"2023-01-29T08:00:00+03:00","light":"dark","condition":"mostly-cloudy","condition_s":"облачно с прояснениями","temp_min":-12,"temp_max":-8,"temp":-11,"humidity":98,"prec_prob":5,"wind_gust":4,"wind_speed":2,"wind_dir":"s","pressure":750,"uvi":0,"feels_like":-15,"comf_idx":5},"43":{"date":"2023-01-29T09:00:00+03:00","light":"light","condition":"mostly-cloudy","condition_s":"облачно с прояснениями","temp_min":-12,"temp_max":-8,"temp":-11,"humidity":98,"prec_prob":5,"wind_gust":4,"wind_speed":2,"wind_dir":"s","pressure":749,"uvi":1,"feels_like":-15,"comf_idx":6},"44":{"date":"2023-01-29T10:00:00+03:00","light":"light","condition":"partly-cloudy","condition_s":"переменная облачность","temp_min":-12,"temp_max":-7,"temp":-9,"humidity":95,"prec_prob":5,"wind_gust":5,"wind_speed":2,"wind_dir":"sw","pressure":749,"uvi":1,"feels_like":-13,"comf_idx":6},"45":{"date":"2023-01-29T11:00:00+03:00","light":"light","condition":"partly-cloudy","condition_s":"переменная облачность","temp_min":-11,"temp_max":-6,"temp":-7,"humidity":92,"prec_prob":5,"wind_gust":5,"wind_speed":3,"wind_dir":"sw","pressure":749,"uvi":1,"feels_like":-12,"comf_idx":6},"46":{"date":"2023-01-29T12:00:00+03:00","light":"light","condition":"partly-cloudy","condition_s":"переменная облачность","temp_min":-11,"temp_max":-5,"temp":-5,"humidity":90,"prec_prob":5,"wind_gust":5,"wind_speed":3,"wind_dir":"sw","pressure":748,"uvi":2,"feels_like":-10,"comf_idx":7},"47":{"date":"2023-01-29T13:00:00+03:00","light":"light","condition":"partly-cloudy","condition_s":"переменная облачность","temp_min":-11,"temp_max":-5,"temp":-5,"humidity":89,"prec_prob":5,"wind_gust":6,"wind_speed":3,"wind_dir":"s","pressure":748,"uvi":2,"feels_like":-9,"comf_idx":6},"48":{"date":"2023-01-29T14:00:00+03:00","light":"light","condition":"partly-cloudy","condition_s":"переменная облачность","temp_min":-11,"temp_max":-5,"temp":-5,"humidity":89,"prec_prob":5,"wind_gust":6,"wind_speed":3,"wind_dir":"s","pressure":747,"uvi":1,"feels_like":-9,"comf_idx":6},"49":{"date":"2023-01-29T15:00:00+03:00","light":"light","condition":"partly-cloudy","condition_s":"переменная облачность","temp_min":-11,"temp_max":-4,"temp":-4,"humidity":89,"prec_prob":5,"wind_gust":6,"wind_speed":3,"wind_dir":"s","pressure":747,"uvi":1,"feels_like":-8,"comf_idx":7},"50":{"date":"2023-01-29T16:00:00+03:00","light":"light","condition":"partly-cloudy","condition_s":"переменная облачность","temp_min":-10,"temp_max":-4,"temp":-5,"humidity":90,"prec_prob":8,"wind_gust":7,"wind_speed":3,"wind_dir":"s","pressure":747,"uvi":1,"feels_like":-9,"comf_idx":6},"51":{"date":"2023-01-29T17:00:00+03:00","light":"dark","condition":"partly-cloudy","condition_s":"переменная облачность","temp_min":-8,"temp_max":-4,"temp":-6,"humidity":92,"prec_prob":8,"wind_gust":7,"wind_speed":3,"wind_dir":"s","pressure":746,"uvi":0,"feels_like":-10,"comf_idx":6},"52":{"date":"2023-01-29T18:00:00+03:00","light":"dark","condition":"partly-cloudy","condition_s":"переменная облачность","temp_min":-7,"temp_max":-4,"temp":-6,"humidity":94,"prec_prob":8,"wind_gust":7,"wind_speed":3,"wind_dir":"s","pressure":746,"uvi":0,"feels_like":-11,"comf_idx":7},"53":{"date":"2023-01-29T19:00:00+03:00","light":"dark","condition":"semitransparent","condition_s":"полупрозрачная облачность","temp_min":-7,"temp_max":-5,"temp":-6,"humidity":94,"prec_prob":6,"wind_gust":8,"wind_speed":3,"wind_dir":"sw","pressure":746,"uvi":0,"feels_like":-10,"comf_idx":6},"54":{"date":"2023-01-29T20:00:00+03:00","light":"dark","condition":"semitransparent","condition_s":"полупрозрачная облачность","temp_min":-7,"temp_max":-5,"temp":-6,"humidity":94,"prec_prob":6,"wind_gust":8,"wind_speed":3,"wind_dir":"sw","pressure":746,"uvi":0,"feels_like":-10,"comf_idx":6},"55":{"date":"2023-01-29T21:00:00+03:00","light":"dark","condition":"semitransparent","condition_s":"полупрозрачная облачность","temp_min":-7,"temp_max":-6,"temp":-6,"humidity":94,"prec_prob":6,"wind_gust":8,"wind_speed":3,"wind_dir":"sw","pressure":745,"uvi":0,"feels_like":-10,"comf_idx":7},"56":{"date":"2023-01-29T22:00:00+03:00","light":"dark","condition":"cloudy","condition_s":"облачно","temp_min":-6,"temp_max":-6,"temp":-6,"humidity":94,"prec_prob":13,"wind_gust":9,"wind_speed":4,"wind_dir":"s","pressure":745,"uvi":0,"feels_like":-10,"comf_idx":5},"57":{"date":"2023-01-29T23:00:00+03:00","light":"dark","condition":"cloudy","condition_s":"облачно","temp_min":-6,"temp_max":-5,"temp":-5,"humidity":94,"prec_prob":13,"wind_gust":9,"wind_speed":4,"wind_dir":"s","pressure":745,"uvi":0,"feels_like":-10,"comf_idx":5},"sunrise":"2023-01-29T08:29:00+03:00","sunset":"2023-01-29T16:56:07+03:00","moonrise":"2023-01-29T11:09:13+03:00","moonset":"2023-01-29T02:07:00+03:00","moon_phase":12},"3":{"58":{"date":"2023-01-30T00:00:00+03:00","light":"dark","condition":"cloudy","condition_s":"облачно","temp_min":-6,"temp_max":-5,"temp":-5,"humidity":94,"prec_prob":13,"wind_gust":9,"wind_speed":4,"wind_dir":"s","pressure":744,"uvi":0,"feels_like":-10,"comf_idx":7},"59":{"date":"2023-01-30T01:00:00+03:00","light":"dark","condition":"cloudy_snow_0","condition_s":"облачно, небольшой снег","temp_min":-6,"temp_max":-5,"temp":-5,"humidity":94,"prec_prob":89,"wind_gust":10,"wind_speed":4,"wind_dir":"s","pressure":744,"uvi":0,"feels_like":-10,"comf_idx":4},"60":{"date":"2023-01-30T02:00:00+03:00","light":"dark","condition":"cloudy_snow_0","condition_s":"облачно, небольшой снег","temp_min":-6,"temp_max":-5,"temp":-5,"humidity":94,"prec_prob":89,"wind_gust":10,"wind_speed":4,"wind_dir":"s","pressure":743,"uvi":0,"feels_like":-10,"comf_idx":4},"61":{"date":"2023-01-30T03:00:00+03:00","light":"dark","condition":"cloudy_snow_0","condition_s":"облачно, небольшой снег","temp_min":-6,"temp_max":-5,"temp":-5,"humidity":94,"prec_prob":89,"wind_gust":10,"wind_speed":5,"wind_dir":"s","pressure":742,"uvi":0,"feels_like":-10,"comf_idx":5},"62":{"date":"2023-01-30T04:00:00+03:00","light":"dark","condition":"cloudy_snow_0","condition_s":"облачно, небольшой снег","temp_min":-6,"temp_max":-5,"temp":-5,"humidity":94,"prec_prob":84,"wind_gust":11,"wind_speed":5,"wind_dir":"s","pressure":742,"uvi":0,"feels_like":-10,"comf_idx":4},"63":{"date":"2023-01-30T05:00:00+03:00","light":"dark","condition":"cloudy_snow_0","condition_s":"облачно, небольшой снег","temp_min":-5,"temp_max":-5,"temp":-5,"humidity":94,"prec_prob":84,"wind_gust":11,"wind_speed":5,"wind_dir":"s","pressure":741,"uvi":0,"feels_like":-10,"comf_idx":4},"64":{"date":"2023-01-30T06:00:00+03:00","light":"dark","condition":"cloudy_snow_0","condition_s":"облачно, небольшой снег","temp_min":-5,"temp_max":-5,"temp":-5,"humidity":93,"prec_prob":84,"wind_gust":11,"wind_speed":5,"wind_dir":"s","pressure":741,"uvi":0,"feels_like":-10,"comf_idx":5},"65":{"date":"2023-01-30T07:00:00+03:00","light":"dark","condition":"cloudy","condition_s":"облачно, без существенных осадков","temp_min":-5,"temp_max":-5,"temp":-5,"humidity":93,"prec_prob":28,"wind_gust":13,"wind_speed":5,"wind_dir":"s","pressure":740,"uvi":0,"feels_like":-10,"comf_idx":4},"66":{"date":"2023-01-30T08:00:00+03:00","light":"dark","condition":"cloudy","condition_s":"облачно, без существенных осадков","temp_min":-5,"temp_max":-5,"temp":-5,"humidity":93,"prec_prob":28,"wind_gust":13,"wind_speed":5,"wind_dir":"s","pressure":740,"uvi":0,"feels_like":-10,"comf_idx":4},"67":{"date":"2023-01-30T09:00:00+03:00","light":"light","condition":"cloudy","condition_s":"облачно, без существенных осадков","temp_min":-5,"temp_max":-5,"temp":-5,"humidity":92,"prec_prob":28,"wind_gust":13,"wind_speed":6,"wind_dir":"s","pressure":740,"uvi":1,"feels_like":-11,"comf_idx":6},"68":{"date":"2023-01-30T10:00:00+03:00","light":"light","condition":"cloudy","condition_s":"облачно, без существенных осадков","temp_min":-5,"temp_max":-4,"temp":-4,"humidity":92,"prec_prob":32,"wind_gust":14,"wind_speed":6,"wind_dir":"s","pressure":739,"uvi":1,"feels_like":-10,"comf_idx":4},"69":{"date":"2023-01-30T11:00:00+03:00","light":"light","condition":"cloudy","condition_s":"облачно, без существенных осадков","temp_min":-5,"temp_max":-4,"temp":-4,"humidity":91,"prec_prob":32,"wind_gust":14,"wind_speed":6,"wind_dir":"s","pressure":739,"uvi":1,"feels_like":-9,"comf_idx":4},"70":{"date":"2023-01-30T12:00:00+03:00","light":"light","condition":"cloudy","condition_s":"облачно, без существенных осадков","temp_min":-5,"temp_max":-3,"temp":-3,"humidity":91,"prec_prob":32,"wind_gust":14,"wind_speed":6,"wind_dir":"s","pressure":738,"uvi":1,"feels_like":-9,"comf_idx":6},"71":{"date":"2023-01-30T13:00:00+03:00","light":"light","condition":"cloudy","condition_s":"облачно, без существенных осадков","temp_min":-4,"temp_max":-3,"temp":-3,"humidity":90,"prec_prob":46,"wind_gust":14,"wind_speed":7,"wind_dir":"s","pressure":738,"uvi":1,"feels_like":-9,"comf_idx":4},"72":{"date":"2023-01-30T14:00:00+03:00","light":"light","condition":"cloudy","condition_s":"облачно, без существенных осадков","temp_min":-4,"temp_max":-2,"temp":-2,"humidity":90,"prec_prob":46,"wind_gust":14,"wind_speed":7,"wind_dir":"s","pressure":737,"uvi":1,"feels_like":-9,"comf_idx":4},"sunrise":"2023-01-30T08:27:14+03:00","sunset":"2023-01-30T16:58:14+03:00","moonrise":"2023-01-30T11:22:48+03:00","moonset":"2023-01-30T03:33:19+03:00","moon_phase":13},"start_date":"2023-01-27T14:00:00+03:00"}}